test/__init__.py
test/unit/__init__.py
test/unit/conftest.py
test/unit/test_client.py
test/unit/test_customers.py
test/unit/test_inventory.py
test/unit/test_locations.py
test/unit/test_tickets.py
tuneuptechnology/__init__.py
tuneuptechnology/client.py
tuneuptechnology/customers.py
tuneuptechnology/inventory.py
tuneuptechnology/locations.py
tuneuptechnology/tickets.py
tuneuptechnology-3.0.0.dist-info/LICENSE
tuneuptechnology-3.0.0.dist-info/METADATA
tuneuptechnology-3.0.0.dist-info/WHEEL
tuneuptechnology-3.0.0.dist-info/top_level.txt
tuneuptechnology-3.0.0.dist-info/RECORD
