Metadata-Version: 2.1
Name: tuneuptechnology
Version: 3.0.0
Summary: The Python client library for the Tuneup Technology App.
Home-page: http://github.com/tuneuptechnology/tuneuptechnology-python
Author: Tuneup Technology
Author-email: tuneuptechnology@gmail.com
License: MIT
Platform: UNKNOWN
Classifier: Programming Language :: Python :: 3
Classifier: License :: OSI Approved :: MIT License
Classifier: Operating System :: OS Independent
Requires-Python: >=3.6
License-File: LICENSE
Requires-Dist: requests (==2.*)
Provides-Extra: dev
Requires-Dist: coveralls (==3.*) ; extra == 'dev'
Requires-Dist: flake8 ; extra == 'dev'
Requires-Dist: mock (==4.*) ; extra == 'dev'
Requires-Dist: pytest (==6.*) ; extra == 'dev'
Requires-Dist: pytest-cov (==2.*) ; extra == 'dev'
Requires-Dist: vcrpy (==4.*) ; extra == 'dev'
